{
    "address_components": [
        {
            "long_name": "16",
            "short_name": "16",
            "types": [
                "street_number"
            ]
        },
        {
            "long_name": "East 103rd Street",
            "short_name": "E 103rd St",
            "types": [
                "route"
            ]
        },
        {
            "long_name": "Manhattan",
            "short_name": "Manhattan",
            "types": [
                "sublocality_level_1",
                "sublocality",
                "political"
            ]
        },
        {
            "long_name": "New York",
            "short_name": "New York",
            "types": [
                "locality",
                "political"
            ]
        },
        {
            "long_name": "New York County",
            "short_name": "New York County",
            "types": [
                "administrative_area_level_2",
                "political"
            ]
        },
        {
            "long_name": "New York",
            "short_name": "NY",
            "types": [
                "administrative_area_level_1",
                "political"
            ]
        },
        {
            "long_name": "United States",
            "short_name": "US",
            "types": [
                "country",
                "political"
            ]
        },
        {
            "long_name": "10029",
            "short_name": "10029",
            "types": [
                "postal_code"
            ]
        }
    ],
    "adr_address": "<span class=\"street-address\">16 E 103rd St</span>, <span class=\"locality\">New York</span>, <span class=\"region\">NY</span> <span class=\"postal-code\">10029</span>, <span class=\"country-name\">USA</span>",
    "formatted_address": "16 E 103rd St, New York, NY 10029, USA",
    "geometry": {
        "location": {
            "lat": 40.79169599999999,
            "lng": -73.951584
        },
        "viewport": {
            "northeast": {
                "lat": 40.7931462802915,
                "lng": -73.95016096970849
            },
            "southwest": {
                "lat": 40.7904483197085,
                "lng": -73.9528589302915
            }
        }
    },
    "icon": "https://maps.gstatic.com/mapfiles/place_api/icons/generic_business-71.png",
    "id": "777a72c3f402c6ef3c91f4195b5dbfee6151382a",
    "name": "Statens Fastighetsverk",
    "place_id": "ChIJ4VHziFdnwokRGZxhXEd0pDc",
    "plus_code": {
        "compound_code": "Q2RX+M9 New York, United States",
        "global_code": "87G8Q2RX+M9"
    },
    "reference": "ChIJ4VHziFdnwokRGZxhXEd0pDc",
    "scope": "GOOGLE",
    "types": [
        "point_of_interest",
        "establishment"
    ],
    "url": "https://maps.google.com/?cid=4009457418107984921",
    "utc_offset": -240,
    "vicinity": "16 East 103rd Street, New York"
}