{
    "address_components": [
        {
            "long_name": "503",
            "short_name": "503",
            "types": [
                "street_number"
            ]
        },
        {
            "long_name": "West 147th Street",
            "short_name": "W 147th St",
            "types": [
                "route"
            ]
        },
        {
            "long_name": "Manhattan",
            "short_name": "Manhattan",
            "types": [
                "sublocality_level_1",
                "sublocality",
                "political"
            ]
        },
        {
            "long_name": "New York",
            "short_name": "New York",
            "types": [
                "locality",
                "political"
            ]
        },
        {
            "long_name": "New York County",
            "short_name": "New York County",
            "types": [
                "administrative_area_level_2",
                "political"
            ]
        },
        {
            "long_name": "New York",
            "short_name": "NY",
            "types": [
                "administrative_area_level_1",
                "political"
            ]
        },
        {
            "long_name": "United States",
            "short_name": "US",
            "types": [
                "country",
                "political"
            ]
        },
        {
            "long_name": "10031",
            "short_name": "10031",
            "types": [
                "postal_code"
            ]
        },
        {
            "long_name": "4424",
            "short_name": "4424",
            "types": [
                "postal_code_suffix"
            ]
        }
    ],
    "adr_address": "<span class=\"street-address\">503 W 147th St</span>, <span class=\"locality\">New York</span>, <span class=\"region\">NY</span> <span class=\"postal-code\">10031-4424</span>, <span class=\"country-name\">USA</span>",
    "formatted_address": "503 W 147th St, New York, NY 10031, USA",
    "formatted_phone_number": "(212) 283-0172",
    "geometry": {
        "location": {
            "lat": 40.8269939,
            "lng": -73.9470463
        },
        "viewport": {
            "northeast": {
                "lat": 40.82822513029149,
                "lng": -73.94578481970849
            },
            "southwest": {
                "lat": 40.82552716970849,
                "lng": -73.9484827802915
            }
        }
    },
    "icon": "https://maps.gstatic.com/mapfiles/place_api/icons/school-71.png",
    "id": "095f8b2b53ec04f20a14043ef4441d10512b470c",
    "international_phone_number": "+1 212-283-0172",
    "name": "Chelsy's Group Family Child Care Corporation",
    "opening_hours": {
        "open_now": false,
        "periods": [
            {
                "close": {
                    "day": 1,
                    "time": "2130"
                },
                "open": {
                    "day": 1,
                    "time": "2000"
                }
            },
            {
                "close": {
                    "day": 2,
                    "time": "2130"
                },
                "open": {
                    "day": 2,
                    "time": "0800"
                }
            },
            {
                "close": {
                    "day": 3,
                    "time": "2100"
                },
                "open": {
                    "day": 3,
                    "time": "0800"
                }
            },
            {
                "close": {
                    "day": 4,
                    "time": "2100"
                },
                "open": {
                    "day": 4,
                    "time": "0800"
                }
            },
            {
                "close": {
                    "day": 5,
                    "time": "2100"
                },
                "open": {
                    "day": 5,
                    "time": "0800"
                }
            }
        ],
        "weekday_text": [
            "Monday: 8:00 \u2013 9:30 PM",
            "Tuesday: 8:00 AM \u2013 9:30 PM",
            "Wednesday: 8:00 AM \u2013 9:00 PM",
            "Thursday: 8:00 AM \u2013 9:00 PM",
            "Friday: 8:00 AM \u2013 9:00 PM",
            "Saturday: Closed",
            "Sunday: Closed"
        ]
    },
    "place_id": "ChIJjxB7L332wokRw-QR8bA5SfE",
    "plus_code": {
        "compound_code": "R3G3+Q5 New York, United States",
        "global_code": "87G8R3G3+Q5"
    },
    "reference": "ChIJjxB7L332wokRw-QR8bA5SfE",
    "scope": "GOOGLE",
    "types": [
        "point_of_interest",
        "establishment"
    ],
    "url": "https://maps.google.com/?cid=17386491268562019523",
    "utc_offset": -300,
    "vicinity": "503 West 147th Street, New York",
    "website": "http://chelsydaycare.com/"
}