{
    "address_components": [
        {
            "long_name": "34",
            "short_name": "34",
            "types": [
                "street_number"
            ]
        },
        {
            "long_name": "West 134th Street",
            "short_name": "W 134th St",
            "types": [
                "route"
            ]
        },
        {
            "long_name": "Manhattan",
            "short_name": "Manhattan",
            "types": [
                "sublocality_level_1",
                "sublocality",
                "political"
            ]
        },
        {
            "long_name": "New York",
            "short_name": "New York",
            "types": [
                "locality",
                "political"
            ]
        },
        {
            "long_name": "New York County",
            "short_name": "New York County",
            "types": [
                "administrative_area_level_2",
                "political"
            ]
        },
        {
            "long_name": "New York",
            "short_name": "NY",
            "types": [
                "administrative_area_level_1",
                "political"
            ]
        },
        {
            "long_name": "United States",
            "short_name": "US",
            "types": [
                "country",
                "political"
            ]
        },
        {
            "long_name": "10037",
            "short_name": "10037",
            "types": [
                "postal_code"
            ]
        },
        {
            "long_name": "2535",
            "short_name": "2535",
            "types": [
                "postal_code_suffix"
            ]
        }
    ],
    "adr_address": "<span class=\"street-address\">34 W 134th St</span>, <span class=\"locality\">New York</span>, <span class=\"region\">NY</span> <span class=\"postal-code\">10037-2535</span>, <span class=\"country-name\">USA</span>",
    "formatted_address": "34 W 134th St, New York, NY 10037, USA",
    "formatted_phone_number": "(212) 862-6401",
    "geometry": {
        "location": {
            "lat": 40.8127334,
            "lng": -73.9398989
        },
        "viewport": {
            "northeast": {
                "lat": 40.8141170302915,
                "lng": -73.93852321970849
            },
            "southwest": {
                "lat": 40.81141906970851,
                "lng": -73.94122118029149
            }
        }
    },
    "icon": "https://maps.gstatic.com/mapfiles/place_api/icons/generic_business-71.png",
    "id": "cf31908a120a794baaff74d026ec971faeef87d0",
    "international_phone_number": "+1 212-862-6401",
    "name": "Lt JP Kennedy Jr Community Center",
    "opening_hours": {
        "open_now": false,
        "periods": [
            {
                "close": {
                    "day": 0,
                    "time": "1930"
                },
                "open": {
                    "day": 0,
                    "time": "0900"
                }
            },
            {
                "close": {
                    "day": 1,
                    "time": "2030"
                },
                "open": {
                    "day": 1,
                    "time": "0800"
                }
            },
            {
                "close": {
                    "day": 2,
                    "time": "2030"
                },
                "open": {
                    "day": 2,
                    "time": "0800"
                }
            },
            {
                "close": {
                    "day": 3,
                    "time": "2030"
                },
                "open": {
                    "day": 3,
                    "time": "0800"
                }
            },
            {
                "close": {
                    "day": 4,
                    "time": "2030"
                },
                "open": {
                    "day": 4,
                    "time": "0800"
                }
            },
            {
                "close": {
                    "day": 5,
                    "time": "2030"
                },
                "open": {
                    "day": 5,
                    "time": "0800"
                }
            },
            {
                "close": {
                    "day": 6,
                    "time": "1930"
                },
                "open": {
                    "day": 6,
                    "time": "0900"
                }
            }
        ],
        "weekday_text": [
            "Monday: 8:00 AM \u2013 8:30 PM",
            "Tuesday: 8:00 AM \u2013 8:30 PM",
            "Wednesday: 8:00 AM \u2013 8:30 PM",
            "Thursday: 8:00 AM \u2013 8:30 PM",
            "Friday: 8:00 AM \u2013 8:30 PM",
            "Saturday: 9:00 AM \u2013 7:30 PM",
            "Sunday: 9:00 AM \u2013 7:30 PM"
        ]
    },
    "photos": [
        {
            "height": 1152,
            "html_attributions": [
                "<a href=\"https://maps.google.com/maps/contrib/113668801424869734531/photos\">Lt JP Kennedy Jr Community Center</a>"
            ],
            "photo_reference": "CmRaAAAAkcFSc_cY8pJCE4zB0iV8gAM5iTRyvbjBt6ObVXW4cju-LDnQ5JPbFj5rxXk44X4Q7rST0z7Ad0t5xN06zkMkcRbZtRzmza3kwJyjiSOZM-eUMzk5U7DxDzWN575gZXgCEhDsYJ2irrDhzC0Qi6BISVIfGhR6PMQQuQGJZ_F8xF8nJfQSRboGDA",
            "width": 2048
        },
        {
            "height": 2767,
            "html_attributions": [
                "<a href=\"https://maps.google.com/maps/contrib/111413535296788792333/photos\">Harold Washington</a>"
            ],
            "photo_reference": "CmRaAAAAsfLBoIimdbshWhBPZBRSywJhobVD07c8NQjHBUMW2_BrVLrKzL7QEigAsNSKz1MWOzPww4GQcElwC-N1XbQi9OKoPs9BAodJXR4pvz52gnll2joxJaRuMI0rM2M6zZNIEhC1qNSh6DfWEOVjS4rSKbV9GhSLByuIX-Wi5is9Epe8FEyBSx72Hg",
            "width": 4281
        },
        {
            "height": 2815,
            "html_attributions": [
                "<a href=\"https://maps.google.com/maps/contrib/111413535296788792333/photos\">Harold Washington</a>"
            ],
            "photo_reference": "CmRaAAAAG3Sfq3Ksz6ug1SFTOQzxjRE-z-LILWyLwGanRobbvXCx2u_V83R2QQaolUPoJsOHkrswN-jhVfHTE7wpESPLT0s7dQjMzlzX3i5gjei2wO8sLBIPjInevMUc2h7gUIbdEhDPVkGTJNRar-793sy_1P2LGhRXL4nB4NdaPwcizaDdccUX_BhbkA",
            "width": 3947
        },
        {
            "height": 3264,
            "html_attributions": [
                "<a href=\"https://maps.google.com/maps/contrib/111413535296788792333/photos\">Harold Washington</a>"
            ],
            "photo_reference": "CmRaAAAAdpz6XTAecSkpepI_VwSgTKkRgfuSzSPPzgJ5jWSoTNVBBsQAY21_vaGCSfQPI6OWW6MXkhps5WKu32ObLqnLdiW7ojOykpU9O5Ica9aULO7ndqeUHqciCI1Tq-TYoCUBEhADG9xp9PBtCBehNHGsev-bGhRGqeArg4XOEjvaaNmYU3_M6WNvFw",
            "width": 1836
        },
        {
            "height": 864,
            "html_attributions": [
                "<a href=\"https://maps.google.com/maps/contrib/111413535296788792333/photos\">Harold Washington</a>"
            ],
            "photo_reference": "CmRaAAAADOEwbGRSpPSN5SYX17LKqCu4hbtOCCLgwhtbB_BSDjyNCzfMxCrCTmozYpA2cxqJuVWyvK6cWPt-5X9qtsM_OBtnXa_7hxF827pjxXOVEO8BM84jfQYVJ8oT85y81DohEhAAzCUezk-C0pd2-lhBrKSpGhQ1HEV_7SXyfiliVN_8cS9bFjgJAw",
            "width": 1152
        },
        {
            "height": 2471,
            "html_attributions": [
                "<a href=\"https://maps.google.com/maps/contrib/111413535296788792333/photos\">Harold Washington</a>"
            ],
            "photo_reference": "CmRaAAAAZegSQtr8YGlNGkFWvX7eq0DiUsQlt5PCD-hEsT8xctWmnH0ge08Q2ja6s70pF1bmdNq-NpaLBL7to1MOijUEUfgQ_lPx8QiOM-UN7yb0ARCOHleCoO4G3IYreoqn7KyvEhDgen9QDhCmu0geroUXzKO-GhSS12ovJnGZrAXaH97VK7cWQjcRYg",
            "width": 4187
        },
        {
            "height": 1152,
            "html_attributions": [
                "<a href=\"https://maps.google.com/maps/contrib/102345290677157251228/photos\">brother anbu</a>"
            ],
            "photo_reference": "CmRaAAAAuyzDQcprWJsfxB-DW4097HR6bodGYTnsc9m9-Hg4m40PN7v7zd_tK4uIzgvZ6filFAMmKHRw4pQ4-dQ_3qizNsAtM6hU8S2hKJQZnICBT1agynO5G6tV70_3dJnGLv1JEhCYfixZSRFGuWW5el7j-ccJGhSkS-7qAurQ5fy8zgyVfEK-CHch8A",
            "width": 2048
        },
        {
            "height": 2212,
            "html_attributions": [
                "<a href=\"https://maps.google.com/maps/contrib/111413535296788792333/photos\">Harold Washington</a>"
            ],
            "photo_reference": "CmRaAAAAjqrKz24SlPEu8ESPt0oBWysWaoMg0okdbILUqYWo2vAWL6n2--II_ShHhsyTfTBOP_rtnKNQPc2-w8kTJjYk_txV0rtc4wCNPVbDLJJU45BFSNf_gJhHCQ-RraesqLZjEhCeLU5qG30BiIHHdApqcjUsGhTTh6t2S62ssU8SeGnoZZO6jNAtZQ",
            "width": 4319
        },
        {
            "height": 4032,
            "html_attributions": [
                "<a href=\"https://maps.google.com/maps/contrib/117865487068712915812/photos\">Colin Rodney</a>"
            ],
            "photo_reference": "CmRaAAAA5D5NLooPfUM5Xg_fkCb4OcVI0M8n6_8GekxEFafL7LV9PkFnGC_Ac9g38nYKqYBwKdmkf0cm_Ss4QbG4t9w7JXHA5gn_gSu9T9jJUNr7E-BU6NJINJpGO4sWwlkuDZj2EhB7DP32hEVmVq8qFnuXbsUXGhQsn-gq_SJjncvvDQ-n4MscB4XZ2A",
            "width": 3024
        },
        {
            "height": 2664,
            "html_attributions": [
                "<a href=\"https://maps.google.com/maps/contrib/111413535296788792333/photos\">Harold Washington</a>"
            ],
            "photo_reference": "CmRaAAAAJSqqO9Vl559PVRPYQsWfxXBUCDBdTpRCCfPgm8YO308hgIok9YLoyQLebZZS3O8AqT6smqHuJsJ596NA67icAVYgkkx81Bx1HHjXYbn8KeOvCRA3xpb7l3LiiZkX9hnvEhAfsZYTeVJmSEAX8Calk8X4GhQpQEwS0kT__pvRyCSCJ43PYWXfHA",
            "width": 4446
        }
    ],
    "place_id": "ChIJixVOJHT2wokRvUXh4kotFkQ",
    "plus_code": {
        "compound_code": "R376+32 New York, United States",
        "global_code": "87G8R376+32"
    },
    "rating": 4.2,
    "reference": "ChIJixVOJHT2wokRvUXh4kotFkQ",
    "reviews": [
        {
            "author_name": "Ellen Jones",
            "author_url": "https://www.google.com/maps/contrib/100586010747689620443/reviews",
            "language": "en",
            "profile_photo_url": "https://lh4.googleusercontent.com/-6M1qstMBTEM/AAAAAAAAAAI/AAAAAAAAAAA/AKxrwcbkrSzoTTMPXK9qdt4ZY4sd07IIBg/s128-c0x00000000-cc-rp-mo/photo.jpg",
            "rating": 5,
            "relative_time_description": "3 months ago",
            "text": "The Kennedy Center is a place like no other n Harlem. There's daycare, programs & services to help families. The center has special section, programs & trips for the most forgotten citizens; the senior citizens. What I enjoy the most are the Healthy Heart Programs conducted at the Lt. Joseph P. Kennedy Center, sponsored by Mt. Sinai Hospital and facilitated by Doctor Fergus & her associates. So many health issues are covered to help anyone to live a healthy and longer life. This month, September, we covered Cholesterol(The Good, The Bad & The Health). We are always given printed materials to follow along with slide presentation. Next month, Healthy Hearts will be covering Breast Cancer. As October is Breast Cancer Awareness Month. The participants are given healthy nourishing food at end of each session. I have enjoyed the Healthy Hearts, since I've learned in-depth what causes many of our health issues. Healthy Heart is the place to be each month. Thank you Doctor Fergus, Elizabeth and Patricia.",
            "time": 1537426222
        },
        {
            "author_name": "Carol Green",
            "author_url": "https://www.google.com/maps/contrib/102873311176989267752/reviews",
            "language": "en",
            "profile_photo_url": "https://lh6.googleusercontent.com/-nPNlk06U6tQ/AAAAAAAAAAI/AAAAAAAAAAA/AKxrwcbRJXaAkqzJyc4eq4FPWj2tDTcXMQ/s128-c0x00000000-cc-rp-mo/photo.jpg",
            "rating": 5,
            "relative_time_description": "3 weeks ago",
            "text": "I ATTEND  A DIABETIC  CLASS, ON  WEDNESDAYS,  AT THE CENTER.  I LIVE AT 14 WEST 103 STREET,  CENTRAL PARK WEST, THAT'S THE REASON I GO TO WEST 135TH STREET, AND SHOP A FINE FARE STORE.",
            "time": 1543605118
        },
        {
            "author_name": "Robert James",
            "author_url": "https://www.google.com/maps/contrib/111588113019942279296/reviews",
            "language": "en",
            "profile_photo_url": "https://lh3.googleusercontent.com/-OHLLg3mjHuY/AAAAAAAAAAI/AAAAAAAAACA/lZrmkcqDKGU/s128-c0x00000000-cc-rp-mo-ba3/photo.jpg",
            "rating": 4,
            "relative_time_description": "a week ago",
            "text": "Nice place to hold events. Parking is limited. Good friendly staff.",
            "time": 1544549739
        },
        {
            "author_name": "Allison Pinkney",
            "author_url": "https://www.google.com/maps/contrib/115371548780157981800/reviews",
            "language": "en",
            "profile_photo_url": "https://lh3.googleusercontent.com/-Auc4AtxdqME/AAAAAAAAAAI/AAAAAAAAAAA/AKxrwcZEjNZz3ZT_EYNZFBl4t6OQrwWWrw/s128-c0x00000000-cc-rp-mo-ba2/photo.jpg",
            "rating": 5,
            "relative_time_description": "a month ago",
            "text": "Love it. So helpful and so many friendly people willing to help you out.",
            "time": 1541001176
        },
        {
            "author_name": "Ryan Hanna",
            "author_url": "https://www.google.com/maps/contrib/110449135515555436556/reviews",
            "language": "en",
            "profile_photo_url": "https://lh3.googleusercontent.com/-mRoTIycG-pw/AAAAAAAAAAI/AAAAAAAAA8k/QrscIVEoR5U/s128-c0x00000000-cc-rp-mo/photo.jpg",
            "rating": 5,
            "relative_time_description": "3 months ago",
            "text": "I volunteer here and the people are so friendly. They make my day when I see them smile.",
            "time": 1537895816
        }
    ],
    "scope": "GOOGLE",
    "types": [
        "point_of_interest",
        "establishment"
    ],
    "url": "https://maps.google.com/?cid=4906158643723978173",
    "utc_offset": -300,
    "vicinity": "34 West 134th Street, New York"
}