{
    "address_components": [
        {
            "long_name": "321",
            "short_name": "321",
            "types": [
                "street_number"
            ]
        },
        {
            "long_name": "6th Avenue",
            "short_name": "6th Ave",
            "types": [
                "route"
            ]
        },
        {
            "long_name": "Manhattan",
            "short_name": "Manhattan",
            "types": [
                "sublocality_level_1",
                "sublocality",
                "political"
            ]
        },
        {
            "long_name": "New York",
            "short_name": "New York",
            "types": [
                "locality",
                "political"
            ]
        },
        {
            "long_name": "New York County",
            "short_name": "New York County",
            "types": [
                "administrative_area_level_2",
                "political"
            ]
        },
        {
            "long_name": "New York",
            "short_name": "NY",
            "types": [
                "administrative_area_level_1",
                "political"
            ]
        },
        {
            "long_name": "United States",
            "short_name": "US",
            "types": [
                "country",
                "political"
            ]
        },
        {
            "long_name": "10014",
            "short_name": "10014",
            "types": [
                "postal_code"
            ]
        },
        {
            "long_name": "6926",
            "short_name": "6926",
            "types": [
                "postal_code_suffix"
            ]
        }
    ],
    "adr_address": "<span class=\"street-address\">321 6th Ave</span>, <span class=\"locality\">New York</span>, <span class=\"region\">NY</span> <span class=\"postal-code\">10014-6926</span>, <span class=\"country-name\">USA</span>",
    "formatted_address": "321 6th Ave, New York, NY 10014, USA",
    "formatted_phone_number": "(212) 255-9888",
    "geometry": {
        "location": {
            "lat": 40.7311027,
            "lng": -74.0016084
        },
        "viewport": {
            "northeast": {
                "lat": 40.7324239302915,
                "lng": -74.00017561970849
            },
            "southwest": {
                "lat": 40.7297259697085,
                "lng": -74.0028735802915
            }
        }
    },
    "icon": "https://maps.gstatic.com/mapfiles/place_api/icons/restaurant-71.png",
    "id": "1692170f0edc06bab957f799e67f60a2df04f0c9",
    "international_phone_number": "+1 212-255-9888",
    "name": "Fay Da Bakery",
    "opening_hours": {
        "open_now": true,
        "periods": [
            {
                "close": {
                    "day": 0,
                    "time": "2000"
                },
                "open": {
                    "day": 0,
                    "time": "0700"
                }
            },
            {
                "close": {
                    "day": 1,
                    "time": "2000"
                },
                "open": {
                    "day": 1,
                    "time": "0700"
                }
            },
            {
                "close": {
                    "day": 2,
                    "time": "2000"
                },
                "open": {
                    "day": 2,
                    "time": "0700"
                }
            },
            {
                "close": {
                    "day": 3,
                    "time": "2000"
                },
                "open": {
                    "day": 3,
                    "time": "0700"
                }
            },
            {
                "close": {
                    "day": 4,
                    "time": "2000"
                },
                "open": {
                    "day": 4,
                    "time": "0700"
                }
            },
            {
                "close": {
                    "day": 5,
                    "time": "2000"
                },
                "open": {
                    "day": 5,
                    "time": "0700"
                }
            },
            {
                "close": {
                    "day": 6,
                    "time": "2000"
                },
                "open": {
                    "day": 6,
                    "time": "0700"
                }
            }
        ],
        "weekday_text": [
            "Monday: 7:00 AM \u2013 8:00 PM",
            "Tuesday: 7:00 AM \u2013 8:00 PM",
            "Wednesday: 7:00 AM \u2013 8:00 PM",
            "Thursday: 7:00 AM \u2013 8:00 PM",
            "Friday: 7:00 AM \u2013 8:00 PM",
            "Saturday: 7:00 AM \u2013 8:00 PM",
            "Sunday: 7:00 AM \u2013 8:00 PM"
        ]
    },
    "photos": [
        {
            "height": 3120,
            "html_attributions": [
                "<a href=\"https://maps.google.com/maps/contrib/102790267567196914801/photos\">Tannic P</a>"
            ],
            "photo_reference": "CmRaAAAAPrkSYNzKa2iDjUS_WS46v4TXbz3ePwVLn7okxz-yMNsE37FE3kPGUBd0ZTZnD4rgHVxwHwAwsAsMTOHippERG2hwwEERMXKeXgR-72hDA4VqEIt_gSjwP2AVz0-pIt-tEhBM1fjA5w9dPpOiRXcNqJXuGhTF60_uXT_kGW5gz5zvBNQOW6lbpw",
            "width": 4160
        },
        {
            "height": 3264,
            "html_attributions": [
                "<a href=\"https://maps.google.com/maps/contrib/117737131764790537177/photos\">Nishat R</a>"
            ],
            "photo_reference": "CmRaAAAARi0B6K192XLxbht0KgqEkC_m9MzbbDFuFcgtEGmzV5GvB-89u7VaBemovvUbdbOrs4RRbRQpGkEhAlTfaRgsB_DsWTZNVblPb35BJSdY03mGEWCnO4bohqGqN9Qa1tO1EhCMXwpLcqqvgs_hly7sRWRwGhS7JuHjduDFIzoBog9zsw1ozAQ2Ww",
            "width": 2448
        },
        {
            "height": 3024,
            "html_attributions": [
                "<a href=\"https://maps.google.com/maps/contrib/100114772565283476838/photos\">Alvin Ho</a>"
            ],
            "photo_reference": "CmRaAAAAMMnKfy5pnaFEq9CJDNaTL2Roy3H0i6nQtdQabIBG9mrygme8I27SfVjphTlDoRZ-m29-7yJp9j_7hSz91ZPDuPxYqtG6hPuM0vMkROKGveAT40lSR_4xobhIJEK-f8lgEhCa8l8vhhh8D_lU0ndlf16fGhRWyc4vNynCn441un0PZWo3y-6LeQ",
            "width": 4032
        },
        {
            "height": 1334,
            "html_attributions": [
                "<a href=\"https://maps.google.com/maps/contrib/117737131764790537177/photos\">Nishat R</a>"
            ],
            "photo_reference": "CmRaAAAADFsaRzCtdhUbKupDbYZums4LbV2Kd1eaQkU-csPS21yX7LLDb8aGzemBYzChxp6E3tGtMMnC0X9iBsMt3d43CFb56DEg-u4vf45YKL2OthWAD7nKB1QuXyO_arLKRSbzEhC_UswBacBriH1BSb_jlphHGhTJFNlqDoo0W8DKkG5Yyg7mOLHlgQ",
            "width": 750
        },
        {
            "height": 2160,
            "html_attributions": [
                "<a href=\"https://maps.google.com/maps/contrib/111046657388603965026/photos\">Malavika Muralidharan</a>"
            ],
            "photo_reference": "CmRaAAAAc34RYWvvkVsrAvjfMgE9Z6ChO1JRByBVXNehhRn6iMyI4r37ytxJ1GIjkAxWOkZjYR_QIWynMJg45qKRzS5NpTuL83XdETyqG2ahM41_6-i5q5RDq7l_p7tDn4ujafinEhBorQP14-0CgUfBZvD80ntDGhSQ3rbrhG1sFcmxkWd3rvm57v1j6Q",
            "width": 3840
        },
        {
            "height": 4032,
            "html_attributions": [
                "<a href=\"https://maps.google.com/maps/contrib/113203458071188658861/photos\">Wenyi Zhou</a>"
            ],
            "photo_reference": "CmRaAAAABQbIcC3GNtW63tFJyj23jfhOKMYDY-OrDYUavcceYP5zW2Iy38uiCXbE2wfnq8PdQnIe05SuvJGcToR4_VyzwPjoKWVwht9DLfGbfuw5Qt58it7dmfKMrLp7S66t_8YBEhAny-u_ZUchJdtoYCykEadKGhSO25NdfB73pIVr7L0Z1VX-YVNnYg",
            "width": 3024
        },
        {
            "height": 2448,
            "html_attributions": [
                "<a href=\"https://maps.google.com/maps/contrib/117737131764790537177/photos\">Nishat R</a>"
            ],
            "photo_reference": "CmRaAAAAeBDgJ5tyEJzAZPv3sMV1p3D96Ne5x750-GWGYKjCM1syh4Zj1_pD6cv7Hwr-marP8hk0lTsLts9NrK3Zusf6Ec2O3dM10xpzwYNsZOsp0ocgy_7w4GlXjOeXWvdvcynDEhBg8ThQ1Cgg1E5tfvQt7q6pGhRF-KM-8W3TJKBbaRBekSmj7VSBfQ",
            "width": 3264
        },
        {
            "height": 3024,
            "html_attributions": [
                "<a href=\"https://maps.google.com/maps/contrib/113887529334451581290/photos\">Jacqui Hertel</a>"
            ],
            "photo_reference": "CmRaAAAACZRuYqj8QqtgnQlpe3u-cHL8fGCrawSdlcReg1Ssu1aVgwkZs8YpBhRh0uX3APMWXe-v3szLpaIVT4VaRLA0zjdaUdwm2ACBGKhBlhVadjm2hBGvHfLtk4hTfLKTQX7KEhCDT9xqKtzSLP1lIDZ3OOhwGhS9Cg1Umtu_M6XB96wuYApD63cIIQ",
            "width": 4032
        },
        {
            "height": 4032,
            "html_attributions": [
                "<a href=\"https://maps.google.com/maps/contrib/108472613319547324951/photos\">Jonathan Ahrens</a>"
            ],
            "photo_reference": "CmRaAAAAoReai3p3AFV2-Yc7usROXf3oUDNuPRKUG1FpNjK-AE9rWOlFDDh7pwH9pxhlVPYJ9dbSOnGCDVviEroYgW3qlVGRfjtdUXaIeM2oVmkw5b4xl64cL19_aBbaQl27wi5vEhDHnEuvEFu6XWKPDcltWyQ7GhT0Iy33KLeN-Y8wyyqZkzOwXMkh6w",
            "width": 3024
        },
        {
            "height": 3840,
            "html_attributions": [
                "<a href=\"https://maps.google.com/maps/contrib/105489725985834357133/photos\">Kevan S</a>"
            ],
            "photo_reference": "CmRaAAAAVwhkVqLfjlSi3FtoAde4hbAcX7Odb5Xdn16tvsAeVHmvOlRisLNWfIkqnm029tfehgMBZ1hs_OrnNvMKWt-BiiKXKFxXv6QrTSbLPbvoM-qUSSkoDdo06yS2I-IimZsSEhAgPt8KLwkk6MSQv--mljoOGhSYkwHfgrA_FPG3R_k8NIL_podKCQ",
            "width": 2160
        }
    ],
    "place_id": "ChIJcZSxyJNZwokRE_3Snje_so4",
    "plus_code": {
        "compound_code": "PXJX+C9 New York, United States",
        "global_code": "87G7PXJX+C9"
    },
    "price_level": 1,
    "rating": 4.4,
    "reference": "ChIJcZSxyJNZwokRE_3Snje_so4",
    "reviews": [
        {
            "author_name": "Yurika Ohno",
            "author_url": "https://www.google.com/maps/contrib/111383530240859450664/reviews",
            "language": "en",
            "profile_photo_url": "https://lh3.googleusercontent.com/-oTSulmUheRQ/AAAAAAAAAAI/AAAAAAAAENc/X6hgJhOVAIo/s128-c0x00000000-cc-rp-mo/photo.jpg",
            "rating": 2,
            "relative_time_description": "3 weeks ago",
            "text": "The attitude was very bad. Not only to me but to every customer at cashier. This cashier woman didn\u2019t listen to carefully and had an attitude to whatever we ask. Maybe you are busy but we are just buying from you. No need to get upset.",
            "time": 1560466957
        },
        {
            "author_name": "Haley Dupree",
            "author_url": "https://www.google.com/maps/contrib/115836287985303475922/reviews",
            "language": "en",
            "profile_photo_url": "https://lh6.googleusercontent.com/-3cfxrn2Tb_8/AAAAAAAAAAI/AAAAAAAAArU/HrtbpqCQQaU/s128-c0x00000000-cc-rp-mo/photo.jpg",
            "rating": 5,
            "relative_time_description": "4 months ago",
            "text": "Fantastic place, so cheap and food is great (for the price).  The rice in lotus leaf is actually stuffed with different kinds of meats -- for like $3 it's a really filling and delicious meal.  Steamed buns are great too.  Surprised this place isn't packed -- so rare to find a cheap place in NYC (I'm talking less than $5 cheap) with food that actually tastes good.",
            "time": 1550194571
        },
        {
            "author_name": "Elsie Boone",
            "author_url": "https://www.google.com/maps/contrib/114924116703218344015/reviews",
            "language": "en",
            "profile_photo_url": "https://lh3.googleusercontent.com/-6NXvtEr0fkc/AAAAAAAAAAI/AAAAAAAAAAo/8rZzddR_bPk/s128-c0x00000000-cc-rp-mo/photo.jpg",
            "rating": 4,
            "relative_time_description": "5 months ago",
            "text": "Good thin crust pizza and bakery goods! Mocha was also pleasant.  Good place to stop by after a walk through golden gate park.  Prices are very reasonable and staff very friendly",
            "time": 1549357247
        },
        {
            "author_name": "Dayana Valeriano",
            "author_url": "https://www.google.com/maps/contrib/108411024875192225840/reviews",
            "language": "en",
            "profile_photo_url": "https://lh4.googleusercontent.com/-N_Jph3CPlHk/AAAAAAAAAAI/AAAAAAAAHm8/VNkltnV2quk/s128-c0x00000000-cc-rp-mo-ba2/photo.jpg",
            "rating": 4,
            "relative_time_description": "a month ago",
            "text": "Very good spongy cakes and crispy pastries from sweet to savory ... VERY AFFORDABLE",
            "time": 1559399909
        },
        {
            "author_name": "Malavika Muralidharan",
            "author_url": "https://www.google.com/maps/contrib/111046657388603965026/reviews",
            "language": "en",
            "profile_photo_url": "https://lh3.googleusercontent.com/-fS_S3CxR6K8/AAAAAAAAAAI/AAAAAAAAAFg/aLGgbF6jHuI/s128-c0x00000000-cc-rp-mo-ba5/photo.jpg",
            "rating": 5,
            "relative_time_description": "4 weeks ago",
            "text": "Love their cakes. I've had their Chocolate Mousse many times in the past few years and it's one awesome melt-in-your-mouth cake! They have tons of other goodies but I haven't got a chance to try anything else since fill up on cake everytime lol. Very convenient location - right outside the subway. They are cash only which is a slight inconvenience but there are ATMs (Chase, Citi) close by.",
            "time": 1560195719
        }
    ],
    "scope": "GOOGLE",
    "types": [
        "bakery",
        "food",
        "store",
        "point_of_interest",
        "establishment"
    ],
    "url": "https://maps.google.com/?cid=10282491144848997651",
    "user_ratings_total": 114,
    "utc_offset": -240,
    "vicinity": "321 6th Avenue, New York",
    "website": "http://www.fayda.com/"
}