{
    "address_components": [
        {
            "long_name": "241",
            "short_name": "241",
            "types": [
                "street_number"
            ]
        },
        {
            "long_name": "West 145th Street",
            "short_name": "W 145th St",
            "types": [
                "route"
            ]
        },
        {
            "long_name": "Manhattan",
            "short_name": "Manhattan",
            "types": [
                "sublocality_level_1",
                "sublocality",
                "political"
            ]
        },
        {
            "long_name": "New York",
            "short_name": "New York",
            "types": [
                "locality",
                "political"
            ]
        },
        {
            "long_name": "New York County",
            "short_name": "New York County",
            "types": [
                "administrative_area_level_2",
                "political"
            ]
        },
        {
            "long_name": "New York",
            "short_name": "NY",
            "types": [
                "administrative_area_level_1",
                "political"
            ]
        },
        {
            "long_name": "United States",
            "short_name": "US",
            "types": [
                "country",
                "political"
            ]
        },
        {
            "long_name": "10039",
            "short_name": "10039",
            "types": [
                "postal_code"
            ]
        }
    ],
    "adr_address": "<span class=\"street-address\">241 W 145th St</span>, <span class=\"locality\">New York</span>, <span class=\"region\">NY</span> <span class=\"postal-code\">10039</span>, <span class=\"country-name\">USA</span>",
    "formatted_address": "241 W 145th St, New York, NY 10039, USA",
    "formatted_phone_number": "(347) 842-5140",
    "geometry": {
        "location": {
            "lat": 40.82261889999999,
            "lng": -73.94100100000001
        },
        "viewport": {
            "northeast": {
                "lat": 40.82390208029149,
                "lng": -73.9397002197085
            },
            "southwest": {
                "lat": 40.82120411970849,
                "lng": -73.9423981802915
            }
        }
    },
    "icon": "https://maps.gstatic.com/mapfiles/place_api/icons/generic_business-71.png",
    "id": "a73cb51058104618bfc29d790aad30dabc90e39a",
    "international_phone_number": "+1 347-842-5140",
    "name": "Chelsea salon",
    "opening_hours": {
        "open_now": false,
        "periods": [
            {
                "close": {
                    "day": 0,
                    "time": "1700"
                },
                "open": {
                    "day": 0,
                    "time": "1000"
                }
            },
            {
                "close": {
                    "day": 2,
                    "time": "1900"
                },
                "open": {
                    "day": 2,
                    "time": "0900"
                }
            },
            {
                "close": {
                    "day": 3,
                    "time": "1900"
                },
                "open": {
                    "day": 3,
                    "time": "0900"
                }
            },
            {
                "close": {
                    "day": 4,
                    "time": "1900"
                },
                "open": {
                    "day": 4,
                    "time": "0900"
                }
            },
            {
                "close": {
                    "day": 5,
                    "time": "1900"
                },
                "open": {
                    "day": 5,
                    "time": "0900"
                }
            },
            {
                "close": {
                    "day": 6,
                    "time": "1900"
                },
                "open": {
                    "day": 6,
                    "time": "0900"
                }
            }
        ],
        "weekday_text": [
            "Monday: Closed",
            "Tuesday: 9:00 AM \u2013 7:00 PM",
            "Wednesday: 9:00 AM \u2013 7:00 PM",
            "Thursday: 9:00 AM \u2013 7:00 PM",
            "Friday: 9:00 AM \u2013 7:00 PM",
            "Saturday: 9:00 AM \u2013 7:00 PM",
            "Sunday: 10:00 AM \u2013 5:00 PM"
        ]
    },
    "photos": [
        {
            "height": 4032,
            "html_attributions": [
                "<a href=\"https://maps.google.com/maps/contrib/107288918804827337252/photos\">Chelsea salon</a>"
            ],
            "photo_reference": "CmRaAAAA2H1I_ziiAKwKHs2rtOU7zr0569sWsEpAar3Yj509g2-09iCqUSQ5zfTBE-zRpfPM-e6I90E0r69OzmeCnmBYP9QheHRtwr7HcR8ULvXMlWURVvwwa7eQhb1TQTGs83pYEhDQyoqqnrrIucq4rKrPVOtAGhQo56vgZLhFL9JhFp6nH97Xh1OGnQ",
            "width": 3024
        },
        {
            "height": 3264,
            "html_attributions": [
                "<a href=\"https://maps.google.com/maps/contrib/107288918804827337252/photos\">Chelsea salon</a>"
            ],
            "photo_reference": "CmRaAAAAjFyTYuOKK7xFRGRU869Ik_E5Tv1G_xI07e8ZkdeCwXZa4oDIQTd6-IUuDklmgH0atxr9cyvWj2zFzunSKF_zzcffqqBYGtY3aMxnYrV4rU7X12UW-n7vWhrsGT1aVfgBEhB7lTl21fLYLTu7sXn4zUkvGhTI4oMjQbcokGqvnxYXUPaedKZETQ",
            "width": 2448
        },
        {
            "height": 3264,
            "html_attributions": [
                "<a href=\"https://maps.google.com/maps/contrib/107288918804827337252/photos\">Chelsea salon</a>"
            ],
            "photo_reference": "CmRaAAAA2YGPVnysI8IskOUQYR_XI3F94uB9v7kJIRUaS-qe7fBNrBM0hAo61FKULlzRBhu8En28WOiKHDa6VRUxZ88cQucwWrbUngR6s4fT5YcS9Is8p6HfG-tdimWqEbWiN5fdEhD-RXuHV7lVjGBboEfFOMm0GhRJDNPBN7pFf-YKED4PeZG4rknABg",
            "width": 2448
        },
        {
            "height": 2048,
            "html_attributions": [
                "<a href=\"https://maps.google.com/maps/contrib/107288918804827337252/photos\">Chelsea salon</a>"
            ],
            "photo_reference": "CmRaAAAAq0AijW5IWy9W4_7iNz4_CKERM0WmFs28ehF1xHwPVo-ub52C_U-dDdzBTnPZleD-EIh0v0vWZcsboPynWejSV7cKg5VzyrK0d9Aws9GzPoL3jt_vv0lxzqFiI-_b1JT-EhAmmpuwdE0nRxq85i6j7yz2GhSCn_7b6VGInx4yv1e6hk5YeHWINQ",
            "width": 1536
        },
        {
            "height": 961,
            "html_attributions": [
                "<a href=\"https://maps.google.com/maps/contrib/107288918804827337252/photos\">Chelsea salon</a>"
            ],
            "photo_reference": "CmRaAAAAevd4KPQs245Gk8A66-EpOrE9W72ks35KUpLjZKHHfNQyI20NHd9HQETaixvEjnBXNWfHm8XlQ-YPuCSPVUdEW9fXfmL0kzx5mKQRx2kaI65F9_3EGtc4L4nKIafvLOE7EhCF4UHDHnH07SLS6RUZcfzbGhS1lwA4PYQHWEsBJS8MFP7M8Cp9KA",
            "width": 961
        },
        {
            "height": 3264,
            "html_attributions": [
                "<a href=\"https://maps.google.com/maps/contrib/107288918804827337252/photos\">Chelsea salon</a>"
            ],
            "photo_reference": "CmRaAAAAXrL5adaMqGQf6EcCwnQM--MT04ZgxONJuszw2sBR7paO7TpH2sU485DyKT3trIDtldBNiE-GXl-bSLfc8ZKXRLy8sCXJBmF7XcAQOa7d3p1cDdHGC4EPYFIbkYQhNcd1EhBfkIfHmGQmhPi6uRH-sQfwGhS2VHS3B93VsRVMI1j3ICmNlCBK-A",
            "width": 2448
        },
        {
            "height": 961,
            "html_attributions": [
                "<a href=\"https://maps.google.com/maps/contrib/107288918804827337252/photos\">Chelsea salon</a>"
            ],
            "photo_reference": "CmRaAAAAc-w3wZc7Ti4K-KHs60cmrRnv5YyOc2ljbfCJQJeNzuZyvZKCQnMgM3EefuPNQil7f4IBdv1aUNCinwzjW1LH6zzGWMoI8-aXdwjLFXmLCw01lH1irrvumK6QFqIASqGjEhBv2khEwAuNcBC4BIwnNNDbGhSS055WybjExkvnba3qZXYewswsSA",
            "width": 960
        }
    ],
    "place_id": "ChIJc3PFSHn2wokRzTaAhykrg1g",
    "plus_code": {
        "compound_code": "R3F5+2H New York, United States",
        "global_code": "87G8R3F5+2H"
    },
    "rating": 5,
    "reference": "ChIJc3PFSHn2wokRzTaAhykrg1g",
    "reviews": [
        {
            "author_name": "Kiwi875",
            "author_url": "https://www.google.com/maps/contrib/105793324938350047132/reviews",
            "language": "en",
            "profile_photo_url": "https://lh6.googleusercontent.com/-caUW85Incxw/AAAAAAAAAAI/AAAAAAAAAAA/AKxrwcZyOX707zew_-exRfXeeuS4AZEfvg/s128-c0x00000000-cc-rp-mo/photo.jpg",
            "rating": 5,
            "relative_time_description": "5 months ago",
            "text": "Big salon with a fun atmosphere.",
            "time": 1531057853
        }
    ],
    "scope": "GOOGLE",
    "types": [
        "beauty_salon",
        "point_of_interest",
        "establishment"
    ],
    "url": "https://maps.google.com/?cid=6377988954653734605",
    "utc_offset": -300,
    "vicinity": "241 West 145th Street, New York",
    "website": "https://chelsea-salon.business.site/"
}