{
    "rating": 3.1, 
    "reference": "ChIJlwplSNBRqEcRJiq-8aec1nA", 
    "place_id": "ChIJlwplSNBRqEcRJiq-8aec1nA", 
    "plus_code": {
        "global_code": "9F4MG96Q+47", 
        "compound_code": "G96Q+47 Berlin, Germany"
    }, 
    "url": "https://maps.google.com/?cid=8130858422393252390", 
    "formatted_address": "Leipziger Str. 120, 10117 Berlin, Germany", 
    "id": "9e427c28e8e0b37b8b6b0950137d8a0266b25ef2", 
    "opening_hours": {
        "weekday_text": [
            "Monday: 10:00 AM \u2013 9:00 PM", 
            "Tuesday: 10:00 AM \u2013 9:00 PM", 
            "Wednesday: 10:00 AM \u2013 9:00 PM", 
            "Thursday: 10:00 AM \u2013 9:00 PM", 
            "Friday: 10:00 AM \u2013 9:00 PM", 
            "Saturday: 10:00 AM \u2013 9:00 PM", 
            "Sunday: 10:00 AM \u2013 9:00 PM"
        ], 
        "open_now": false, 
        "periods": [
            {
                "close": {
                    "day": 0, 
                    "time": "2100"
                }, 
                "open": {
                    "day": 0, 
                    "time": "1000"
                }
            }, 
            {
                "close": {
                    "day": 1, 
                    "time": "2100"
                }, 
                "open": {
                    "day": 1, 
                    "time": "1000"
                }
            }, 
            {
                "close": {
                    "day": 2, 
                    "time": "2100"
                }, 
                "open": {
                    "day": 2, 
                    "time": "1000"
                }
            }, 
            {
                "close": {
                    "day": 3, 
                    "time": "2100"
                }, 
                "open": {
                    "day": 3, 
                    "time": "1000"
                }
            }, 
            {
                "close": {
                    "day": 4, 
                    "time": "2100"
                }, 
                "open": {
                    "day": 4, 
                    "time": "1000"
                }
            }, 
            {
                "close": {
                    "day": 5, 
                    "time": "2100"
                }, 
                "open": {
                    "day": 5, 
                    "time": "1000"
                }
            }, 
            {
                "close": {
                    "day": 6, 
                    "time": "2100"
                }, 
                "open": {
                    "day": 6, 
                    "time": "1000"
                }
            }
        ]
    }, 
    "vicinity": "Leipziger Stra\u00dfe 120, Berlin", 
    "scope": "GOOGLE", 
    "website": "http://www.pension-varna.de/", 
    "utc_offset": 120, 
    "user_ratings_total": 7, 
    "photos": [
        {
            "photo_reference": "CmRaAAAAUNvs4xoX4chyO0etWdfKPLK_PjNXKCExVxXeDB-f_RJz_lxLlSpSd1iwTVpuBoUf7i9P_Qg3afke8X5Mjr2KW4jUmrzDhN5Uycfa301cxvfPrFx1tbih1n03uTAY9stNEhD3M2yltK4XCFlmwtrT55BFGhQBaUkYYDvKYXNjgAX51tK-FDIQfQ", 
            "width": 2340, 
            "html_attributions": [
                "<a href=\"https://maps.google.com/maps/contrib/108181036356278526640/photos\">Henny Bendig</a>"
            ], 
            "height": 4160
        }, 
        {
            "photo_reference": "CmRaAAAAdiaLjTe_hTKgRtxyCV19xsiM-nwqnxlkDL8bhcqghOdYShUSXiqQTM2JcYLiqHq7F0tHKbylCxNOjizHF6pmfpK7b099E9ktLtpzNWEAvSy-xl5o5Uam2FCXKu_GuC3UEhCFgd43c11irNitEQVPyxHYGhRkfOovumJInZnDeSarEZzo2Sb21Q", 
            "width": 2588, 
            "html_attributions": [
                "<a href=\"https://maps.google.com/maps/contrib/100830325366307341539/photos\">rudi kaatz</a>"
            ], 
            "height": 1489
        }, 
        {
            "photo_reference": "CmRaAAAA7fYDR7UYFvQyUC5U38WyO1Rc66sHl23fhh7eCZIMayQAUXd62rgyN6YH09PMeGxij0n6TbM3ssTc3FTj_hZdXoSbNmHoy_cXXvUY3j2IIc3QOmKd6FhDcMaPNXOk2hp6EhAsKlcFQuLjlRpx6tSm4cDYGhRPLj0aFxhZ3zweXSI-JmApBVHILg", 
            "width": 3024, 
            "html_attributions": [
                "<a href=\"https://maps.google.com/maps/contrib/112032980111513951297/photos\">K</a>"
            ], 
            "height": 4032
        }, 
        {
            "photo_reference": "CmRaAAAAL6FMP7wUAEl_lOpAnG89UI_hkMHBkWgJDuGn0KJGJjtS4UmaTYkM_CkkHY3Bj-pvBgFmuktm5eJnL1BbkoCEmfkKnR1pJxflrhblXzalHljsuzrJDoa6AhqJlEObFbEMEhAKnpb464hpJUMYTcX6CYMVGhQmgBJ73GGi6jFAiAhy_F3k5P3zUw", 
            "width": 3024, 
            "html_attributions": [
                "<a href=\"https://maps.google.com/maps/contrib/112032980111513951297/photos\">K</a>"
            ], 
            "height": 4032
        }
    ], 
    "types": [
        "lodging", 
        "point_of_interest", 
        "establishment"
    ], 
    "icon": "https://maps.gstatic.com/mapfiles/place_api/icons/lodging-71.png", 
    "name": "Pension VARNA", 
    "geometry": {
        "location": {
            "lat": 52.51031099999999, 
            "lng": 13.388184
        }, 
        "viewport": {
            "northeast": {
                "lat": 52.51162798029149, 
                "lng": 13.3895382302915
            }, 
            "southwest": {
                "lat": 52.50893001970849, 
                "lng": 13.3868402697085
            }
        }
    }, 
    "adr_address": "<span class=\"street-address\">Leipziger Str. 120</span>, <span class=\"postal-code\">10117</span> <span class=\"locality\">Berlin</span>, <span class=\"country-name\">Germany</span>", 
    "international_phone_number": "+49 30 69207150", 
    "reviews": [
        {
            "rating": 5, 
            "author_name": "Alexander Zarchev", 
            "language": "bg", 
            "text": "\u0421\u0442\u0440\u0430\u0445\u043e\u0442\u043d\u043e \u043c\u044f\u0441\u0442\u043e \u043d\u0430 \u043f\u044a\u043f\u0430 \u043d\u0430 \u0411\u0435\u0440\u043b\u0438\u043d. \u0425\u0430\u0437\u044f\u0438\u043d\u0430 \u0435 \u0441\u0443\u043f\u0435\u0440. \u041f\u0440\u0435\u043f\u043e\u0440\u044a\u0447\u0432\u0430\u043c \u0433\u043e \u043d\u0430 \u0432\u0441\u0435\u043a\u0438.", 
            "relative_time_description": "5 months ago", 
            "author_url": "https://www.google.com/maps/contrib/113112725541789216466/reviews", 
            "time": 1546510776, 
            "profile_photo_url": "https://lh4.googleusercontent.com/-cTJQcryFcsE/AAAAAAAAAAI/AAAAAAAAAAA/ACHi3rfwpk4ehU6vQNfA2mDRTvIqlIxcMQ/s128-c0x00000000-cc-rp-mo-ba5/photo.jpg"
        }, 
        {
            "rating": 5, 
            "author_name": "Flammly M\u00f6zes", 
            "language": "de", 
            "text": "Ich liebe es auch in der Au\u00dfengestaltung haben sie sich auf jeden fall sehr verbessert sieht echt schon aus und top lage", 
            "relative_time_description": "a year ago", 
            "author_url": "https://www.google.com/maps/contrib/118053581823786217396/reviews", 
            "time": 1527507233, 
            "profile_photo_url": "https://lh6.googleusercontent.com/-3dOFrVSdsbI/AAAAAAAAAAI/AAAAAAAAA04/B_xKzyBJQIE/s128-c0x00000000-cc-rp-mo-ba4/photo.jpg"
        }, 
        {
            "rating": 1, 
            "author_name": "Peto Urban", 
            "language": "de", 
            "text": "Bild ist super aber realitet eine grosse katastrofe !!!!!!! Nicht mehr", 
            "relative_time_description": "a year ago", 
            "author_url": "https://www.google.com/maps/contrib/114600857891248194039/reviews", 
            "time": 1512019640, 
            "profile_photo_url": "https://lh5.googleusercontent.com/-5A5mrt4K8Fg/AAAAAAAAAAI/AAAAAAAAAAA/ACHi3reip20KEgqC22nB0MfCgT1NE3-fSg/s128-c0x00000000-cc-rp-mo/photo.jpg"
        }, 
        {
            "rating": 1, 
            "profile_photo_url": "https://lh5.googleusercontent.com/-ooAYxeiiT3Y/AAAAAAAAAAI/AAAAAAAAAAA/ACHi3reyX4ny62NkrsDVe90bHf3oe_R5HQ/s128-c0x00000000-cc-rp-mo/photo.jpg", 
            "author_name": "mihailescu florin", 
            "text": "", 
            "relative_time_description": "a month ago", 
            "author_url": "https://www.google.com/maps/contrib/109399671724204995071/reviews", 
            "time": 1557035803
        }, 
        {
            "rating": 5, 
            "profile_photo_url": "https://lh6.googleusercontent.com/-3413gg_Ik4E/AAAAAAAAAAI/AAAAAAAAE9M/T4qeqG5Ei-g/s128-c0x00000000-cc-rp-mo-ba2/photo.jpg", 
            "author_name": "Sefer Tuten", 
            "text": "", 
            "relative_time_description": "9 months ago", 
            "author_url": "https://www.google.com/maps/contrib/101930012852472622685/reviews", 
            "time": 1535788486
        }
    ], 
    "formatted_phone_number": "030 69207150", 
    "address_components": [
        {
            "long_name": "120", 
            "types": [
                "street_number"
            ], 
            "short_name": "120"
        }, 
        {
            "long_name": "Leipziger Stra\u00dfe", 
            "types": [
                "route"
            ], 
            "short_name": "Leipziger Str."
        }, 
        {
            "long_name": "Bezirk Mitte", 
            "types": [
                "sublocality_level_1", 
                "sublocality", 
                "political"
            ], 
            "short_name": "Bezirk Mitte"
        }, 
        {
            "long_name": "Berlin", 
            "types": [
                "locality", 
                "political"
            ], 
            "short_name": "Berlin"
        }, 
        {
            "long_name": "Berlin", 
            "types": [
                "administrative_area_level_1", 
                "political"
            ], 
            "short_name": "Berlin"
        }, 
        {
            "long_name": "Germany", 
            "types": [
                "country", 
                "political"
            ], 
            "short_name": "DE"
        }, 
        {
            "long_name": "10117", 
            "types": [
                "postal_code"
            ], 
            "short_name": "10117"
        }
    ]
}